multigrid/__init__.py
multigrid/base.py
multigrid/wrappers.py
multigrid/core/__init__.py
multigrid/core/actions.py
multigrid/core/agent.py
multigrid/core/constants.py
multigrid/core/grid.py
multigrid/core/mission.py
multigrid/core/roomgrid.py
multigrid/core/world_object.py
multigrid/envs/__init__.py
multigrid/envs/blockedunlockpickup.py
multigrid/envs/empty.py
multigrid/envs/locked_hallway.py
multigrid/envs/playground.py
multigrid/envs/redbluedoors.py
multigrid/pettingzoo/__init__.py
multigrid/rllib/__init__.py
multigrid/rllib/models.py
multigrid/utils/__init__.py
multigrid/utils/enum.py
multigrid/utils/minigrid_interface.py
multigrid/utils/misc.py
multigrid/utils/obs.py
multigrid/utils/random.py
multigrid/utils/rendering.py
multigrid-0.1.0.dist-info/LICENSE
multigrid-0.1.0.dist-info/METADATA
multigrid-0.1.0.dist-info/WHEEL
multigrid-0.1.0.dist-info/top_level.txt
multigrid-0.1.0.dist-info/RECORD
